barbet/__init__.py
barbet/apps.py
barbet/data.py
barbet/embedding.py
barbet/embeddings/__init__.py
barbet/embeddings/esm.py
barbet/markers.py
barbet/models.py
barbet/modules.py
barbet/output.py
barbet-0.1.1.dist-info/LICENSE
barbet-0.1.1.dist-info/METADATA
barbet-0.1.1.dist-info/WHEEL
barbet-0.1.1.dist-info/entry_points.txt
barbet-0.1.1.dist-info/RECORD
