Metadata-Version: 2.3
Name: Barbet
Version: 0.1.1
Summary: Bacteria and Archaea Representation using Bidirectional Embeddings for Taxonomic classification
License: Apache-2.0
Keywords: torchapp,pytorch,deep learning,command-line interface
Author: Robert Turnbull,  Mar Quiroga, Gabriele Marini, Torsten Seemann, Wytamma Wirth
Requires-Python: >=3.10,<3.13
Classifier: Intended Audience :: Science/Research
Classifier: License :: OSI Approved :: Apache Software License
Classifier: Programming Language :: Python :: 3
Classifier: Programming Language :: Python :: 3.10
Classifier: Programming Language :: Python :: 3.11
Classifier: Programming Language :: Python :: 3.12
Classifier: Topic :: Scientific/Engineering :: Artificial Intelligence
Classifier: Topic :: Software Development :: Libraries :: Python Modules
Requires-Dist: biopython (>=1.79)
Requires-Dist: hierarchicalsoftmax (>=1.4.3)
Requires-Dist: lightning (>=2.3.3)
Requires-Dist: polars (>=1.31.0)
Requires-Dist: torch (==2.2.0)
Requires-Dist: torchapp (>=0.5.7)
Project-URL: Documentation, https://houndry.github.io/barbet
Project-URL: Homepage, https://github.com/houndry/barbet/
Project-URL: Repository, https://github.com/houndry/barbet/
